claude_multiagent_pm-1.4.7.dist-info/licenses/LICENSE
claude_pm/__init__.py
claude_pm/__main__.py
claude_pm/_version.py
claude_pm/cli.py
claude_pm/cli_deployment_integration.py
claude_pm/cli_enforcement.py
claude_pm/cli_enhanced_flags.py
claude_pm/cli_flags.py
claude_pm/cmpm_commands.py
claude_pm/py.typed
claude_pm/adapters/__init__.py
claude_pm/adapters/health_adapter.py
claude_pm/agents/__init__.py
claude_pm/agents/agent_loader.py
claude_pm/agents/agent_loader_integration.py
claude_pm/agents/agents_metadata.py
claude_pm/agents/base_agent.md
claude_pm/agents/base_agent_loader.py
claude_pm/agents/system_agent_config.py
claude_pm/agents/.claude-pm/config/project.json
claude_pm/agents/templates/README.md
claude_pm/agents/templates/__init__.py
claude_pm/agents/templates/data_engineer_agent.md
claude_pm/agents/templates/documentation_agent.md
claude_pm/agents/templates/engineer_agent.md
claude_pm/agents/templates/ops_agent.md
claude_pm/agents/templates/qa_agent.md
claude_pm/agents/templates/research_agent.md
claude_pm/agents/templates/security_agent.md
claude_pm/agents/templates/ticketing_agent.md
claude_pm/agents/templates/version_control_agent.md
claude_pm/agents/test_fix_deployment/.claude-pm/config/project.json
claude_pm/api/__init__.py
claude_pm/api/memory_endpoints.py
claude_pm/cli/MODEL_FLAG_IMPLEMENTATION_SUMMARY.md
claude_pm/cli/MODEL_INTEGRATION_EXAMPLE.md
claude_pm/cli/VERSION
claude_pm/cli/__init__.py
claude_pm/cli/__main__.py
claude_pm/cli/cli_utils.py
claude_pm/cli/deployment_commands.py
claude_pm/cli/productivity_commands.py
claude_pm/cli/setup_commands.py
claude_pm/cli/system_commands.py
claude_pm/cli/test_commands.py
claude_pm/collectors/__init__.py
claude_pm/collectors/framework_services.py
claude_pm/commands/__init__.py
claude_pm/commands/dependency_manager.py
claude_pm/commands/health_commands.py
claude_pm/commands/template_commands.py
claude_pm/config/README.md
claude_pm/config/__init__.py
claude_pm/config/async_memory_config.py
claude_pm/config/default_model_config.py
claude_multiagent_pm-1.4.7.dist-info/METADATA
claude_multiagent_pm-1.4.7.dist-info/WHEEL
claude_multiagent_pm-1.4.7.dist-info/entry_points.txt
claude_multiagent_pm-1.4.7.dist-info/top_level.txt
claude_multiagent_pm-1.4.7.dist-info/RECORD
