Metadata-Version: 2.4
Name: claude-multiagent-pm
Version: 1.4.7
Summary: Claude Multi-Agent Project Management Framework for AI-driven orchestration
Author-email: "Robert (Masa) Matsuoka" <masa@matsuoka.com>
Maintainer-email: "Robert (Masa) Matsuoka" <masa@matsuoka.com>
License: MIT
Project-URL: Homepage, https://github.com/bobmatnyc/claude-multiagent-pm
Project-URL: Documentation, https://github.com/bobmatnyc/claude-multiagent-pm#readme
Project-URL: Repository, https://github.com/bobmatnyc/claude-multiagent-pm.git
Project-URL: Bug Reports, https://github.com/bobmatnyc/claude-multiagent-pm/issues
Project-URL: Changelog, https://github.com/bobmatnyc/claude-multiagent-pm/blob/main/docs/CHANGELOG.md
Project-URL: Source Code, https://github.com/bobmatnyc/claude-multiagent-pm
Project-URL: Releases, https://github.com/bobmatnyc/claude-multiagent-pm/releases
Keywords: claude,project-management,ai-orchestration,multi-agent,agent-framework,subprocess-coordination,development-framework,automation,trackdown,task-management,mem0ai,llm,ai-agents,workflow-automation,developer-tools,devops,ci-cd,code-generation,documentation-automation
Classifier: Development Status :: 4 - Beta
Classifier: Intended Audience :: Developers
Classifier: Intended Audience :: Information Technology
Classifier: Intended Audience :: System Administrators
Classifier: License :: OSI Approved :: MIT License
Classifier: Operating System :: OS Independent
Classifier: Operating System :: POSIX :: Linux
Classifier: Operating System :: MacOS :: MacOS X
Classifier: Operating System :: Microsoft :: Windows
Classifier: Programming Language :: Python :: 3
Classifier: Programming Language :: Python :: 3.9
Classifier: Programming Language :: Python :: 3.10
Classifier: Programming Language :: Python :: 3.11
Classifier: Programming Language :: Python :: 3.12
Classifier: Programming Language :: Python :: 3 :: Only
Classifier: Topic :: Software Development :: Libraries :: Python Modules
Classifier: Topic :: Software Development :: Libraries :: Application Frameworks
Classifier: Topic :: Software Development :: Build Tools
Classifier: Topic :: Software Development :: Code Generators
Classifier: Topic :: Software Development :: Quality Assurance
Classifier: Topic :: Software Development :: Testing
Classifier: Topic :: Software Development :: Version Control :: Git
Classifier: Topic :: Scientific/Engineering :: Artificial Intelligence
Classifier: Topic :: System :: Distributed Computing
Classifier: Topic :: System :: Systems Administration
Classifier: Topic :: Utilities
Classifier: Environment :: Console
Classifier: Framework :: AsyncIO
Classifier: Natural Language :: English
Classifier: Typing :: Typed
Requires-Python: >=3.9
License-File: LICENSE
Requires-Dist: aiohttp>=3.9.0
Requires-Dist: asyncio-mqtt>=0.16.0
Requires-Dist: click>=8.1.0
Requires-Dist: pydantic>=2.5.0
Requires-Dist: rich>=13.7.0
Requires-Dist: typer>=0.9.0
Requires-Dist: pyyaml>=6.0.1
Requires-Dist: toml>=0.10.2
Requires-Dist: python-dotenv>=1.0.0
Requires-Dist: psutil>=5.9.0
Requires-Dist: httpx>=0.25.0
Requires-Dist: openai>=1.0.0
Requires-Dist: requests>=2.31.0
Requires-Dist: pathspec>=0.11.0
Requires-Dist: ai-trackdown-pytools==1.1.0
Requires-Dist: python-frontmatter>=1.0.0
Requires-Dist: mistune>=3.0.0
Requires-Dist: tree-sitter>=0.20.0
Requires-Dist: tree-sitter-python>=0.20.0
Requires-Dist: tree-sitter-javascript>=0.20.0
Requires-Dist: tree-sitter-typescript>=0.20.0
Provides-Extra: dev
Requires-Dist: pytest>=7.4.0; extra == "dev"
Requires-Dist: pytest-asyncio>=0.21.0; extra == "dev"
Requires-Dist: pytest-cov>=4.1.0; extra == "dev"
Requires-Dist: pytest-mock>=3.11.0; extra == "dev"
Requires-Dist: coverage[toml]>=7.3.0; extra == "dev"
Requires-Dist: black>=23.9.0; extra == "dev"
Requires-Dist: isort>=5.12.0; extra == "dev"
Requires-Dist: flake8>=6.1.0; extra == "dev"
Requires-Dist: mypy>=1.6.0; extra == "dev"
Requires-Dist: pre-commit>=3.5.0; extra == "dev"
Requires-Dist: mkdocs>=1.5.0; extra == "dev"
Requires-Dist: mkdocs-material>=9.4.0; extra == "dev"
Requires-Dist: mkdocstrings[python]>=0.23.0; extra == "dev"
Requires-Dist: ipython>=8.16.0; extra == "dev"
Requires-Dist: jupyter>=1.0.0; extra == "dev"
Requires-Dist: python-dotenv>=1.0.0; extra == "dev"
Provides-Extra: production
Requires-Dist: sentry-sdk>=1.38.0; extra == "production"
Requires-Dist: prometheus-client>=0.18.0; extra == "production"
Requires-Dist: gunicorn>=21.2.0; extra == "production"
Requires-Dist: uvicorn[standard]>=0.24.0; extra == "production"
Requires-Dist: redis>=5.0.0; extra == "production"
Requires-Dist: psycopg2-binary>=2.9.0; extra == "production"
Provides-Extra: ai
Requires-Dist: mem0ai>=0.1.0; extra == "ai"
Requires-Dist: openai>=1.0.0; extra == "ai"
Requires-Dist: anthropic>=0.7.0; extra == "ai"
Requires-Dist: chromadb>=0.4.0; extra == "ai"
Requires-Dist: faiss-cpu>=1.7.0; extra == "ai"
Requires-Dist: tiktoken>=0.5.0; extra == "ai"
Requires-Dist: transformers>=4.35.0; extra == "ai"
Provides-Extra: evaluation
Requires-Dist: mirascope>=0.1.0; extra == "evaluation"
Requires-Dist: pydantic>=2.5.0; extra == "evaluation"
Requires-Dist: asyncio>=3.4.0; extra == "evaluation"
Provides-Extra: all
Requires-Dist: claude-multiagent-pm[ai,dev,evaluation,production]; extra == "all"
Dynamic: license-file
